babel_edtf/__init__.py
babel_edtf/version.py
babel_edtf-1.2.1.dist-info/AUTHORS.rst
babel_edtf-1.2.1.dist-info/LICENSE
babel_edtf-1.2.1.dist-info/METADATA
babel_edtf-1.2.1.dist-info/WHEEL
babel_edtf-1.2.1.dist-info/top_level.txt
babel_edtf-1.2.1.dist-info/RECORD
