Metadata-Version: 2.1
Name: babel-edtf
Version: 1.2.1
Summary: Localization of Extended Date Time Format level 0 strings.
Home-page: https://github.com/inveniosoftware/babel-edtf
Author: CERN
Author-email: info@inveniosoftware.org
License: MIT
Keywords: babel l10n edtf
Platform: any
Classifier: Intended Audience :: Developers
Classifier: License :: OSI Approved :: MIT License
Classifier: Operating System :: OS Independent
Classifier: Programming Language :: Python
Classifier: Programming Language :: Python :: 3
Classifier: Programming Language :: Python :: 3.6
Classifier: Programming Language :: Python :: 3.7
Classifier: Programming Language :: Python :: 3.8
Requires-Dist: Babel >=2.12
Requires-Dist: edtf <6.0.0,>=5.0.0
Provides-Extra: all
Requires-Dist: Sphinx <6,>=5 ; extra == 'all'
Requires-Dist: check-manifest >=0.42 ; extra == 'all'
Requires-Dist: coverage <6,>=5.3 ; extra == 'all'
Requires-Dist: pytest-cov >=2.10.1 ; extra == 'all'
Requires-Dist: pytest-isort >=1.2.0 ; extra == 'all'
Requires-Dist: pytest-pycodestyle >=2.2.0 ; extra == 'all'
Requires-Dist: pytest-pydocstyle >=2.3.2 ; extra == 'all'
Requires-Dist: pytest <8,>=7 ; extra == 'all'
Provides-Extra: docs
Requires-Dist: Sphinx <6,>=5 ; extra == 'docs'
Provides-Extra: tests
Requires-Dist: check-manifest >=0.42 ; extra == 'tests'
Requires-Dist: coverage <6,>=5.3 ; extra == 'tests'
Requires-Dist: pytest-cov >=2.10.1 ; extra == 'tests'
Requires-Dist: pytest-isort >=1.2.0 ; extra == 'tests'
Requires-Dist: pytest-pycodestyle >=2.2.0 ; extra == 'tests'
Requires-Dist: pytest-pydocstyle >=2.3.2 ; extra == 'tests'
Requires-Dist: pytest <8,>=7 ; extra == 'tests'
